[
  {
    "responseId": "ACYDBNg8zI5oyPGrLbCqhGuPPFl0Gv4xuFHOa239iS2bTQt_O_YdAwbjmIOQOjvCeVEa0LI",
    "createTime": "2024-06-06T09:33:21.995Z",
    "lastSubmittedTime": "2024-06-06T09:33:21.995663Z",
    "answers": {
      "4c8e84c8": {
        "questionId": "4c8e84c8",
        "textAnswers": {
          "answers": [
            {
              "value": "Madrid"
            }
          ]
        }
      },
      "063ba149": {
        "questionId": "063ba149",
        "textAnswers": {
          "answers": [
            {
              "value": "Madrid"
            }
          ]
        }
      }
    }
  }
]